traffic_light_controller_part2_starter.sv
// traffic light controller solution stretch
// CSE140L 3-street, 20-state version, ew str/left decouple
// inserts all-red after each yellow
// uses enumerated variables for states and for red-yellow-green
// 5 after traffic, 10 max cycles for green when other traffic present
import light_package ::*;           // defines red, yellow, green

// same as Harris & Harris 4-state, but we have added two all-reds
module traffic_light_controller(
  input clk, reset, e_str_sensor, w_str_sensor, e_left_sensor, 
        w_left_sensor, ns_sensor,             // traffic sensors, east-west str, east-west left, north-south 
  output colors e_str_light, w_str_light, e_left_light, w_left_light, ns_light);     // traffic lights, east-west str, east-west left, north-south

  logic s, sb, e, eb, w, wb, l, lb, n, nb;	 // shorthand for traffic combinations:

  assign s  = e_str_sensor || w_str_sensor;					 // str E or W
  assign sb = e_left_sensor || w_left_sensor || ns_sensor;			     // 3 directions which conflict with s
  assign e  = e_left_sensor || e_str_sensor;					     // E str or L
  assign eb = w_left_sensor || w_str_sensor || ns_sensor;			 // conflicts with e
  assign w  = w_left_sensor || w_str_sensor;
  assign wb = e_left_sensor || e_str_sensor || ns_sensor;
  assign l  = e_left_sensor || w_left_sensor;
  assign lb = e_str_sensor || w_str_sensor || ns_sensor;
  assign n  = ns_sensor;
  assign nb = s || l; 

// 20 suggested states, 4 per direction   Y, Z = easy way to get 2-second yellows
// HRRRR = red-red following ZRRRR; ZRRRR = second yellow following YRRRR; 
// RRRRH = red-red following RRRRZ;
  typedef enum {GRRRR, YRRRR, ZRRRR, HRRRR, 	           // ES+WS
  	            RGRRR, RYRRR, RZRRR, RHRRR, 			   // EL+ES
	            RRGRR, RRYRR, RRZRR, RRHRR,				   // WL+WS
	            RRRGR, RRRYR, RRRZR, RRRHR, 			   // WL+EL
	            RRRRG, RRRRY, RRRRZ, RRRRH} tlc_states;    // NS
	tlc_states    present_state, next_state;
	integer ctr5, next_ctr5,       //  5 sec timeout when my traffic goes away
			ctr10, next_ctr10;     // 10 sec limit when other traffic presents

// sequential part of our state machine (register between C1 and C2 in Harris & Harris Moore machine diagram
// combinational part will reset or increment the counters and figure out the next_state
  always_ff @(posedge clk)
	if(reset) begin
	  present_state <= RRRRH;
	  ctr5          <= 0;
	  ctr10         <= 0;
	end  
	else begin
	  present_state <= next_state;
	  ctr5          <= next_ctr5;
	  ctr10         <= next_ctr10;
	end  

// combinational part of state machine ("C1" block in the Harris & Harris Moore machine diagram)
// default needed because only 6 of 8 possible states are defined/used
  always_comb begin
	next_state = RRRRH;                            // default to reset state
	next_ctr5  = 0; 							   // default: reset counters
	next_ctr10 = 0;
	case(present_state)
/* ************* Fill in the case statements ************** */
	  GRRRR: begin /* fill in the guts
			   build on part 1
			   round-robin priority for four other direcions
                */
        if(ctr5==0 && !s)
            next_ctr5 = ctr5+1;
          else if(ctr5!=0)
            next_ctr5 = ctr5+1;
          else
            next_ctr5 = ctr5; //Still traffic, hasn't started
        //Check to begin ctr10 counter
        if(ctr10==0 && sb)
          next_ctr10 = ctr10+1;
        else if(ctr10!=0)
          next_ctr10 = ctr10+1;
        else
          next_ctr10 = ctr10; //No opposing traffic, hasn't started
        //Check counters
        if(ctr5==4 | ctr10==9) begin
          next_state=YRRRR;
          next_ctr5 = 0;
          next_ctr10 = 0;
        end
          else
            next_state=GRRRR;
	         end      
      YRRRR: begin
        next_state=ZRRRR;
      end
      ZRRRR: begin
        next_state=HRRRR;
      end
      HRRRR: begin
        if(e)
          next_state=RGRRR;
        else if(w)
          next_state=RRGRR;
        else if(l)
          next_state=RRRGR;
        else if(n)
          next_state=RRRRG;
        else if(s)
          next_state=GRRRR;
        else
          next_state=HRRRR;
      end
	  RGRRR: begin 		                                 // EL+ES green
        if(ctr5==0 && !e)
            next_ctr5 = ctr5+1;
          else if(ctr5!=0)
            next_ctr5 = ctr5+1;
          else
            next_ctr5 = ctr5; //Still traffic, hasn't started
        //Check to begin ctr10 counter
        if(ctr10==0 && eb)
          next_ctr10 = ctr10+1;
        else if(ctr10!=0)
          next_ctr10 = ctr10+1;
        else
          next_ctr10 = ctr10; //No opposing traffic, hasn't started
        //Check counters
        if(ctr5==4 | ctr10==9) begin
          next_state=RYRRR;
          next_ctr5 = 0;
          next_ctr10 = 0;
        end
          else
            next_state=RGRRR;
	         end
	  RYRRR: next_state = RZRRR;
	  RZRRR: next_state = RHRRR;
	  RHRRR: begin
        if(w)
          next_state=RRGRR;
        else if(l)
          next_state=RRRGR;
        else if(n)
          next_state=RRRRG;
        else if(s)
          next_state=GRRRR;
        else if(e)
          next_state=RGRRR;
        else
          next_state=RHRRR;
      end

	  RRGRR: begin 
	            
        if(ctr5==0 && !w)
            next_ctr5 = ctr5+1;
          else if(ctr5!=0)
            next_ctr5 = ctr5+1;
          else
            next_ctr5 = ctr5; //Still traffic, hasn't started
        //Check to begin ctr10 counter
        if(ctr10==0 && wb)
          next_ctr10 = ctr10+1;
        else if(ctr10!=0)
          next_ctr10 = ctr10+1;
        else
          next_ctr10 = ctr10; //No opposing traffic, hasn't started
        //Check counters
        if(ctr5==4 | ctr10==9) begin
          next_state=RRYRR;
          next_ctr5 = 0;
          next_ctr10 = 0;
        end
          else
            next_state=RRGRR;
	  end
      RRYRR: next_state=RRZRR;
      RRZRR: next_state=RRHRR;
      RRHRR: begin
        if(l)
          next_state=RRRGR;
        else if(n)
          next_state=RRRRG;
        else if(s)
          next_state=GRRRR;
        else if(e)
          next_state=RGRRR;
        else if(w)
          next_state=RRGRR;
        else
          next_state=RRHRR;
      end
      RRRGR: begin
        if(ctr5==0 && !l)
            next_ctr5 = ctr5+1;
          else if(ctr5!=0)
            next_ctr5 = ctr5+1;
          else
            next_ctr5 = ctr5; //Still traffic, hasn't started
        //Check to begin ctr10 counter
        if(ctr10==0 && lb)
          next_ctr10 = ctr10+1;
        else if(ctr10!=0)
          next_ctr10 = ctr10+1;
        else
          next_ctr10 = ctr10; //No opposing traffic, hasn't started
        //Check counters
        if(ctr5==4 | ctr10==9) begin
          next_state=RRRYR;
          next_ctr5 = 0;
          next_ctr10 = 0;
        end
        else next_state=RRRGR;
      end
      RRRYR: next_state=RRRZR;
      RRRZR: next_state=RRRHR;
      RRRHR: begin
        if(n)
          next_state=RRRRG;
        else if(s)
          next_state=GRRRR;
        else if(e)
          next_state=RGRRR;
        else if(w)
          next_state=RRGRR;
        else if(l)
          next_state=RRRGR;
        else
          next_state=RRRHR;
      end
      RRRRG: begin
        if(ctr5==0 && !n)
            next_ctr5 = ctr5+1;
          else if(ctr5!=0)
            next_ctr5 = ctr5+1;
          else
            next_ctr5 = ctr5; //Still traffic, hasn't started
        //Check to begin ctr10 counter
        if(ctr10==0 && nb)
          next_ctr10 = ctr10+1;
        else if(ctr10!=0)
          next_ctr10 = ctr10+1;
        else
          next_ctr10 = ctr10; //No opposing traffic, hasn't started
        //Check counters
        if(ctr5==4 | ctr10==9) begin
          next_state=RRRRY;
          next_ctr5 = 0;
          next_ctr10 = 0;
      	end
        else next_state=RRRRG;
      end
      RRRRY: next_state=RRRRZ;
      RRRRZ: next_state=RRRRH;
      RRRRH: begin
        if(s)
          next_state=GRRRR;
        else if(e)
          next_state=RGRRR;
        else if(w)
          next_state=RRGRR;
        else if(l)
          next_state=RRRGR;
        else if(n)
          next_state=RRRRG;
        else
          next_state=RRRRH;
      end
        endcase
  end

// combination output driver  ("C2" block in the Harris & Harris Moore machine diagram)
	always_comb begin
	  e_str_light  = red;                // cover all red plus undefined cases
	  w_str_light  = red;				 // no need to list them below this block
	  e_left_light = red;
	  w_left_light = red;
	  ns_light     = red;
	  case(present_state)      // Moore machine
		GRRRR:   begin e_str_light = green;
					   w_str_light = green;
		end
        YRRRR,ZRRRR: begin
          e_str_light = yellow;
		  w_str_light = yellow;
        end
        HRRRR: begin
          e_str_light = red;
		  w_str_light = red;
        end
        RGRRR: begin
        //EL+ES [GREEN]
        e_left_light = green;
        e_str_light = green;  
        end
        RYRRR,RZRRR: begin 
          //EL+ES [YELLOW]
          e_left_light = yellow;
          e_str_light = yellow;
        end
        //WL+WS [GREEN]
        RRGRR: begin 
          w_str_light = green;
          w_left_light = green;
        end
        //WL+WS [YELLOW]
        RRYRR,RRZRR: begin 
          w_left_light = yellow;
          w_str_light = yellow;
          
        end
        //WL+EL [GREEN]
        RRRGR: begin 
          w_left_light = green;
          e_left_light = green;
          
        end
        //WL+EL [YELLOW]
        RRRYR, RRRZR: begin
          w_left_light = yellow; 
          e_left_light = yellow;
          
        end
        //North South [GREEN]
        RRRRG: ns_light = green;
        //North South [YELLOW]
        RRRRY, RRRRZ: ns_light = yellow;
        RRRRH: ns_light=red;
          
      // ** fill in the guts for all 5 directions -- just the greens and yellows **
      endcase
        end
        

endmodule

lab3_part2_tb_file.sv
// test bench 2 for Lab 3 stretch with independent left/straight
// CSE140L   
// expanded version -- try the simpler traffic_tb first if
//  you do not pass this one
// CSE140L   Lab 3   stretch
import light_package ::*;
module lab3_part2_tbf;

logic clk = 0,
      reset = 1,			  // should put your design in all-red
      e_left_sensor = 0,	  // e-bound left turn traffic
	  e_str_sensor  = 0,	  // e-bound thru traffic
	  w_left_sensor = 0,	  // w-bound left turn traffic
	  w_str_sensor  = 0,      // w-bound thru traffic
	  ns_sensor     = 0;      // traffic on n-s street
colors e_left_light,           // left arrow e turn onto n
	  e_str_light,	          // straight ahead e
	  w_left_light,           // left arrow w turn onto s
	  w_str_light,            // straight ahead w
	  ns_light;	              // n-s (no left/thru differentiation)

// your controller goes here
// input ports = logics above
// output ports = colors (enums) above (each 2 bits wide)
traffic_light_controller dut(.*);

colors e_l, e_s, w_l, w_s, ns;
assign e_l = e_left_light;
assign e_s = e_str_light ;
assign w_l = w_left_light;
assign w_s = w_str_light ;
assign ns  = ns_light    ;

int fi;
always begin
  #3ns; 
// print active sensors into result file
  if(e_left_sensor)
    $fwrite(fi,"el  ");
  else
    $fwrite(fi,"    ");
  if(e_str_sensor)
    $fwrite(fi,"es  ");
  else
    $fwrite(fi,"    ");
  if(w_left_sensor)
    $fwrite(fi,"wl  ");
  else
    $fwrite(fi,"    ");
  if(w_str_sensor)
    $fwrite(fi,"ws  ");
  else
    $fwrite(fi,"    ");
  if(ns_sensor)
    $fwrite(fi,"ns  ");
  else
    $fwrite(fi,"    ");
  $fwrite(fi,"    ");
// print yellow and green states into result file
  case(e_left_light)
	green:   $fwrite(fi, "elg   ");
	yellow:	 $fwrite(fi, "ely   ");
	default: $fwrite(fi, "      ");
  endcase
  case(e_str_light)
	green:   $fwrite(fi, "esg   ");
	yellow:	 $fwrite(fi, "esy   ");
	default: $fwrite(fi, "      ");
  endcase
  case(w_left_light)
	green:   $fwrite(fi, "wlg   ");
	yellow:	 $fwrite(fi, "wly   ");
	default: $fwrite(fi, "      ");
  endcase
  case(w_str_light)
	green:   $fwrite(fi, "wsg   ");
	yellow:	 $fwrite(fi, "wsy   ");
	default: $fwrite(fi, "      ");
  endcase
  case(ns_light)
    green:   $fdisplay(fi, "nsg   %t",$time);
	yellow:  $fdisplay(fi, "nsy   %t",$time);
	default: $fdisplay(fi, "      %t",$time);
  endcase
  if(e_left_light && (w_str_light || ns_light)) $fdisplay(fi, "*****error*****");
  if(w_left_light && (e_str_light || ns_light)) $fdisplay(fi, "*****error*****");
  if(w_str_light && ns_light) 				   $fdisplay(fi, "*****error*****");
  if(e_str_light && ns_light)                  $fdisplay(fi, "*****error*****");
  #2ns clk = 1'b1;
  #5ns clk = 1'b0;
/*  case({ew_left_light,ew_str_light,ns_light})
    6'b00_00_00: $fdisplay(fi, "           %t",$time);
	6'b01_00_00: $fdisplay(fi, "y          %t",$time);
	6'b10_00_00: $fdisplay(fi, "g          %t",$time);
	6'b00_01_00: $fdisplay(fi, "   y       %t",$time);
	6'b00_10_00: $fdisplay(fi, "   g       %t",$time);
	6'b00_00_01: $fdisplay(fi, "       y   %t",$time);
	6'b00_00_10: $fdisplay(fi, "       g   %t",$time);
	default    : $fdisplay(fi, "***ERROR** %t",$time);
  endcase 	 */
end

logic [3:0] test_cnt;          // lets testbench track tests
initial begin
  $dumpfile("dump.vcd");
  $dumpvars;
  fi = $fopen("lab3_rslt1_stretch.txt","w");
  $fdisplay(fi, "e   e   w   w   n        e     e     w     w     n");	   // header for y, g status display
  $fdisplay(fi, "l   s   l   s   s        l     s     l     s     s");
  test_cnt       = 4'd0;
  #20ns reset    = 1'b0;
  #10ns;
// Test E_LEFT to W_STR without more traffic
  test_cnt++                 ;
  e_left_sensor       = 1'b1 ;
  #30ns w_left_sensor = 1'b1 ;
  #60ns e_left_sensor = 1'b0 ;
  #20ns e_str_sensor  = 1'b1 ;
  #30ns w_str_sensor  = 1'b1 ;
  #60ns e_str_sensor  = 1'b0 ;
  #10ns w_str_sensor  = 1'b0;
  #30ns w_left_sensor = 1'b0;
  #200ns;

// Now set traffic at NS. Green NS lasts past sensor falling
  test_cnt++                  ;
  ns_sensor           = 1'b1  ;
  #60ns ns_sensor     = 1'b0  ;
  #200ns;

// Check NS again, but hold for more than 5 cycles.
//   NS should cycle green-yellow-red when side traffic appears
  test_cnt++;
  ns_sensor              = 1'b1;
  #100ns e_left_sensor   = 1'b1;
  #200ns ns_sensor       = 1'b0;
  #20ns  e_left_sensor   = 1'b0;
  #100ns;

// All five sensors become 1 at once.
//  EW_STR should come first, then LEFT, then NS
  test_cnt++;
  e_left_sensor  = 1'b1;
  e_str_sensor   = 1'b1;
  w_left_sensor  = 1'b1;
  w_str_sensor   = 1'b1;
  ns_sensor      = 1'b1;
  #1000ns;
  w_left_sensor  = 1'b0;
  #200ns;
  e_str_sensor   = 1'b0;
  ns_sensor      = 1'b0;
  #40ns;
  w_str_sensor   = 1'b0;
  #20ns;
  e_left_sensor  = 1'b0;
  #200ns;

// All
  test_cnt++;
  $stop;
end

endmodule

dump.vcd
$date
	Wed Jul 26 17:31:43 2023
$end
$version
	QuestaSim Version 2021.3
$end
$timescale
	1ns
$end

$scope module lab3_part2_tbf $end
$var reg 1 ! clk $end
$var reg 1 " reset $end
$var reg 1 # e_left_sensor $end
$var reg 1 $ e_str_sensor $end
$var reg 1 % w_left_sensor $end
$var reg 1 & w_str_sensor $end
$var reg 1 ' ns_sensor $end
$var reg 2 ( e_left_light [1:0] $end
$var reg 2 ) e_str_light [1:0] $end
$var reg 2 * w_left_light [1:0] $end
$var reg 2 + w_str_light [1:0] $end
$var reg 2 , ns_light [1:0] $end
$var reg 2 - e_l [1:0] $end
$var reg 2 . e_s [1:0] $end
$var reg 2 / w_l [1:0] $end
$var reg 2 0 w_s [1:0] $end
$var reg 2 1 ns [1:0] $end
$var integer 32 2 fi $end
$var reg 4 3 test_cnt [3:0] $end

$scope module dut $end
$var wire 1 4 clk $end
$var wire 1 5 reset $end
$var wire 1 6 e_str_sensor $end
$var wire 1 7 w_str_sensor $end
$var wire 1 8 e_left_sensor $end
$var wire 1 9 w_left_sensor $end
$var wire 1 : ns_sensor $end
$var reg 2 ; e_str_light [1:0] $end
$var reg 2 < w_str_light [1:0] $end
$var reg 2 = e_left_light [1:0] $end
$var reg 2 > w_left_light [1:0] $end
$var reg 2 ? ns_light [1:0] $end
$var reg 1 @ s $end
$var reg 1 A sb $end
$var reg 1 B e $end
$var reg 1 C eb $end
$var reg 1 D w $end
$var reg 1 E wb $end
$var reg 1 F l $end
$var reg 1 G lb $end
$var reg 1 H n $end
$var reg 1 I nb $end
$var integer 32 J present_state $end
$var integer 32 K next_state $end
$var integer 32 L ctr5 $end
$var integer 32 M next_ctr5 $end
$var integer 32 N ctr10 $end
$var integer 32 O next_ctr10 $end
$upscope $end
$upscope $end

$scope begin light_package $end
$upscope $end

$scope begin testbench_sv_unit $end
$upscope $end

$scope begin std $end
$upscope $end

$scope begin design_sv_unit $end
$upscope $end
$enddefinitions $end
#0
$dumpvars
0!
1"
0#
0$
0%
0&
0'
b0 (
b10 )
b0 *
b10 +
b0 ,
b10 ;
b10 <
b0 =
b0 >
b0 ?
0@
0A
0B
0C
0D
0E
0F
0G
0H
0I
b0 -
b10 .
b0 /
b10 0
b0 1
b0 3
b0 J
b0 K
bx L
bx M
bx N
bx O
b10000000000000000000000000000011 2
0:
09
08
07
06
15
04
$end
#5
1!
14
b10011 J
b0 L
b0 N
b10011 K
b0 M
b0 O
b0 ;
b0 <
b0 +
b0 )
b0 .
b0 0
#10
0!
04
#15
1!
14
#20
0"
0!
05
04
#25
1!
14
#30
b1 3
1#
0!
18
1F
1E
1B
1A
04
1I
b100 K
#35
1!
14
b100 J
b10011 K
b100 K
b10 =
b10 ;
b10 )
b10 (
b10 -
b10 .
#40
0!
04
#45
1!
14
#50
0!
04
#55
1!
14
#60
1%
0!
19
1D
1C
04
b10011 K
b1 O
b100 K
#65
1!
14
b1 N
b10011 K
b0 O
b10 O
b100 K
#70
0!
04
#75
1!
14
b10 N
b10011 K
b0 O
b11 O
b100 K
#80
0!
04
#85
1!
14
b11 N
b10011 K
b0 O
b100 O
b100 K
#90
0!
04
#95
1!
14
b100 N
b10011 K
b0 O
b101 O
b100 K
#100
0!
04
#105
1!
14
b101 N
b10011 K
b0 O
b110 O
b100 K
#110
0!
04
#115
1!
14
b110 N
b10011 K
b0 O
b111 O
b100 K
#120
0#
0!
08
0E
0B
04
b10011 K
b0 O
b1 M
b111 O
b100 K
#125
1!
14
b1 L
b111 N
b10011 K
b0 M
b0 O
b10 M
b1000 O
b100 K
#130
0!
04
#135
1!
14
b10 L
b1000 N
b10011 K
b0 M
b0 O
b11 M
b1001 O
b100 K
#140
1$
0!
16
1G
1E
1B
1@
04
b10011 K
b0 M
b0 O
b11 M
b1001 O
b100 K
#145
1!
14
b11 L
b1001 N
b10011 K
b0 M
b0 O
b100 M
b1010 O
b101 K
b0 M
b0 O
#150
0!
04
#155
1!
14
b101 J
b0 L
b0 N
b10011 K
b110 K
b0 ;
b0 =
b1 =
b1 ;
b1 (
b1 )
b1 .
b1 -
#160
0!
04
#165
1!
14
b110 J
b10011 K
b111 K
b0 ;
b0 =
b1 =
b1 ;
#170
1&
0!
17
04
#175
1!
14
b111 J
b10011 K
b1000 K
b0 ;
b0 =
b0 (
b0 )
b0 .
b0 -
#180
0!
04
#185
1!
14
b1000 J
b10011 K
b1 O
b1000 K
b10 <
b10 >
b10 *
b10 +
b10 0
b10 /
#190
0!
04
#195
1!
14
b1 N
b10011 K
b0 O
b10 O
b1000 K
#200
0!
04
#205
1!
14
b10 N
b10011 K
b0 O
b11 O
b1000 K
#210
0!
04
#215
1!
14
b11 N
b10011 K
b0 O
b100 O
b1000 K
#220
0!
04
#225
1!
14
b100 N
b10011 K
b0 O
b101 O
b1000 K
#230
0$
0!
06
0E
0B
04
b10011 K
b0 O
b101 O
b1000 K
#235
1!
14
b101 N
b10011 K
b0 O
b110 O
b1000 K
#240
0&
0!
07
0G
0@
04
b10011 K
b0 O
b110 O
b1000 K
#245
1!
14
b110 N
b10011 K
b0 O
b111 O
b1000 K
#250
0!
04
#255
1!
14
b111 N
b10011 K
b0 O
b1000 O
b1000 K
#260
0!
04
#265
1!
14
b1000 N
b10011 K
b0 O
b1001 O
b1000 K
#270
0%
0!
09
0F
0D
0C
0A
04
0I
b10011 K
b0 O
b1 M
b1001 O
b1000 K
#275
1!
14
b1 L
b1001 N
b10011 K
b0 M
b0 O
b10 M
b1010 O
b1001 K
b0 M
b0 O
#280
0!
04
#285
1!
14
b1001 J
b0 L
b0 N
b10011 K
b1010 K
b0 <
b0 >
b1 >
b1 <
b1 *
b1 +
b1 0
b1 /
#290
0!
04
#295
1!
14
b1010 J
b10011 K
b1011 K
b0 <
b0 >
b1 >
b1 <
#300
0!
04
#305
1!
14
b1011 J
b10011 K
b1011 K
b0 <
b0 >
b0 *
b0 +
b0 0
b0 /
#310
0!
04
#315
1!
14
#320
0!
04
#325
1!
14
#330
0!
04
#335
1!
14
#340
0!
04
#345
1!
14
#350
0!
04
#355
1!
14
#360
0!
04
#365
1!
14
#370
0!
04
#375
1!
14
#380
0!
04
#385
1!
14
#390
0!
04
#395
1!
14
#400
0!
04
#405
1!
14
#410
0!
04
#415
1!
14
#420
0!
04
#425
1!
14
#430
0!
04
#435
1!
14
#440
0!
04
#445
1!
14
#450
0!
04
#455
1!
14
#460
0!
04
#465
1!
14
#470
b10 3
1'
0!
1:
1H
1G
1E
1C
1A
04
b10011 K
b10000 K
#475
1!
14
b10000 J
b10011 K
b10000 K
b10 ?
b10 ,
b10 1
#480
0!
04
#485
1!
14
#490
0!
04
#495
1!
14
#500
0!
04
#505
1!
14
#510
0!
04
#515
1!
14
#520
0!
04
#525
1!
14
#530
0'
0!
0:
0H
0G
0E
0C
0A
04
b10011 K
b1 M
b10000 K
#535
1!
14
b1 L
b10011 K
b0 M
b10 M
b10000 K
#540
0!
04
#545
1!
14
b10 L
b10011 K
b0 M
b11 M
b10000 K
#550
0!
04
#555
1!
14
b11 L
b10011 K
b0 M
b100 M
b10000 K
#560
0!
04
#565
1!
14
b100 L
b10011 K
b0 M
b101 M
b10001 K
b0 M
#570
0!
04
#575
1!
14
b10001 J
b0 L
b10011 K
b10010 K
b0 ?
b1 ?
b1 ,
b1 1
#580
0!
04
#585
1!
14
b10010 J
b10011 K
b0 ?
b1 ?
#590
0!
04
#595
1!
14
b10011 J
b0 ?
b0 ,
b0 1
#600
0!
04
#605
1!
14
#610
0!
04
#615
1!
14
#620
0!
04
#625
1!
14
#630
0!
04
#635
1!
14
#640
0!
04
#645
1!
14
#650
0!
04
#655
1!
14
#660
0!
04
#665
1!
14
#670
0!
04
#675
1!
14
#680
0!
04
#685
1!
14
#690
0!
04
#695
1!
14
#700
0!
04
#705
1!
14
#710
0!
04
#715
1!
14
#720
0!
04
#725
1!
14
#730
b11 3
1'
0!
1:
1H
1G
1E
1C
1A
04
b10000 K
#735
1!
14
b10000 J
b10011 K
b10000 K
b10 ?
b10 ,
b10 1
#740
0!
04
#745
1!
14
#750
0!
04
#755
1!
14
#760
0!
04
#765
1!
14
#770
0!
04
#775
1!
14
#780
0!
04
#785
1!
14
#790
0!
04
#795
1!
14
#800
0!
04
#805
1!
14
#810
0!
04
#815
1!
14
#820
0!
04
#825
1!
14
#830
1#
0!
18
1F
1B
04
1I
b10011 K
b1 O
b10000 K
#835
1!
14
b1 N
b10011 K
b0 O
b10 O
b10000 K
#840
0!
04
#845
1!
14
b10 N
b10011 K
b0 O
b11 O
b10000 K
#850
0!
04
#855
1!
14
b11 N
b10011 K
b0 O
b100 O
b10000 K
#860
0!
04
#865
1!
14
b100 N
b10011 K
b0 O
b101 O
b10000 K
#870
0!
04
#875
1!
14
b101 N
b10011 K
b0 O
b110 O
b10000 K
#880
0!
04
#885
1!
14
b110 N
b10011 K
b0 O
b111 O
b10000 K
#890
0!
04
#895
1!
14
b111 N
b10011 K
b0 O
b1000 O
b10000 K
#900
0!
04
#905
1!
14
b1000 N
b10011 K
b0 O
b1001 O
b10000 K
#910
0!
04
#915
1!
14
b1001 N
b10011 K
b0 O
b1010 O
b10001 K
b0 O
#920
0!
04
#925
1!
14
b10001 J
b0 N
b10011 K
b10010 K
b0 ?
b1 ?
b1 ,
b1 1
#930
0!
04
#935
1!
14
b10010 J
b10011 K
b0 ?
b1 ?
#940
0!
04
#945
1!
14
b10011 J
b100 K
b0 ?
b0 ,
b0 1
#950
0!
04
#955
1!
14
b100 J
b10011 K
b1 O
b100 K
b10 =
b10 ;
b10 )
b10 (
b10 -
b10 .
#960
0!
04
#965
1!
14
b1 N
b10011 K
b0 O
b10 O
b100 K
#970
0!
04
#975
1!
14
b10 N
b10011 K
b0 O
b11 O
b100 K
#980
0!
04
#985
1!
14
b11 N
b10011 K
b0 O
b100 O
b100 K
#990
0!
04
#995
1!
14
b100 N
b10011 K
b0 O
b101 O
b100 K
#1000
0!
04
#1005
1!
14
b101 N
b10011 K
b0 O
b110 O
b100 K
#1010
0!
04
#1015
1!
14
b110 N
b10011 K
b0 O
b111 O
b100 K
#1020
0!
04
#1025
1!
14
b111 N
b10011 K
b0 O
b1000 O
b100 K
#1030
0'
0!
0:
0H
0G
0C
04
b10011 K
b0 O
b1000 O
b100 K
#1035
1!
14
b1000 N
b10011 K
b0 O
b1001 O
b100 K
#1040
0!
04
#1045
1!
14
b1001 N
b10011 K
b0 O
b1010 O
b101 K
b0 O
#1050
0#
0!
08
0F
0E
0B
0A
04
0I
b10011 K
b1 M
b1010 O
b101 K
b0 M
b0 O
#1055
1!
14
b101 J
b0 N
b10011 K
b110 K
b0 ;
b0 =
b1 =
b1 ;
b1 (
b1 )
b1 .
b1 -
#1060
0!
04
#1065
1!
14
b110 J
b10011 K
b111 K
b0 ;
b0 =
b1 =
b1 ;
#1070
0!
04
#1075
1!
14
b111 J
b10011 K
b111 K
b0 ;
b0 =
b0 (
b0 )
b0 .
b0 -
#1080
0!
04
#1085
1!
14
#1090
0!
04
#1095
1!
14
#1100
0!
04
#1105
1!
14
#1110
0!
04
#1115
1!
14
#1120
0!
04
#1125
1!
14
#1130
0!
04
#1135
1!
14
#1140
0!
04
#1145
1!
14
#1150
b100 3
1#
1$
1%
1&
1'
0!
18
16
19
17
1:
1H
1D
1C
1G
1@
1F
1E
1B
1A
04
1I
b10011 K
b1000 K
#1155
1!
14
b1000 J
b10011 K
b1 O
b1000 K
b10 <
b10 >
b10 *
b10 +
b10 0
b10 /
#1160
0!
04
#1165
1!
14
b1 N
b10011 K
b0 O
b10 O
b1000 K
#1170
0!
04
#1175
1!
14
b10 N
b10011 K
b0 O
b11 O
b1000 K
#1180
0!
04
#1185
1!
14
b11 N
b10011 K
b0 O
b100 O
b1000 K
#1190
0!
04
#1195
1!
14
b100 N
b10011 K
b0 O
b101 O
b1000 K
#1200
0!
04
#1205
1!
14
b101 N
b10011 K
b0 O
b110 O
b1000 K
#1210
0!
04
#1215
1!
14
b110 N
b10011 K
b0 O
b111 O
b1000 K
#1220
0!
04
#1225
1!
14
b111 N
b10011 K
b0 O
b1000 O
b1000 K
#1230
0!
04
#1235
1!
14
b1000 N
b10011 K
b0 O
b1001 O
b1000 K
#1240
0!
04
#1245
1!
14
b1001 N
b10011 K
b0 O
b1010 O
b1001 K
b0 O
#1250
0!
04
#1255
1!
14
b1001 J
b0 N
b10011 K
b1010 K
b0 <
b0 >
b1 >
b1 <
b1 *
b1 +
b1 0
b1 /
#1260
0!
04
#1265
1!
14
b1010 J
b10011 K
b1011 K
b0 <
b0 >
b1 >
b1 <
#1270
0!
04
#1275
1!
14
b1011 J
b10011 K
b1100 K
b0 <
b0 >
b0 *
b0 +
b0 0
b0 /
#1280
0!
04
#1285
1!
14
b1100 J
b10011 K
b1 O
b1100 K
b10 >
b10 =
b10 (
b10 *
b10 /
b10 -
#1290
0!
04
#1295
1!
14
b1 N
b10011 K
b0 O
b10 O
b1100 K
#1300
0!
04
#1305
1!
14
b10 N
b10011 K
b0 O
b11 O
b1100 K
#1310
0!
04
#1315
1!
14
b11 N
b10011 K
b0 O
b100 O
b1100 K
#1320
0!
04
#1325
1!
14
b100 N
b10011 K
b0 O
b101 O
b1100 K
#1330
0!
04
#1335
1!
14
b101 N
b10011 K
b0 O
b110 O
b1100 K
#1340
0!
04
#1345
1!
14
b110 N
b10011 K
b0 O
b111 O
b1100 K
#1350
0!
04
#1355
1!
14
b111 N
b10011 K
b0 O
b1000 O
b1100 K
#1360
0!
04
#1365
1!
14
b1000 N
b10011 K
b0 O
b1001 O
b1100 K
#1370
0!
04
#1375
1!
14
b1001 N
b10011 K
b0 O
b1010 O
b1101 K
b0 O
#1380
0!
04
#1385
1!
14
b1101 J
b0 N
b10011 K
b1110 K
b0 =
b0 >
b1 >
b1 =
b1 *
b1 (
b1 -
b1 /
#1390
0!
04
#1395
1!
14
b1110 J
b10011 K
b1111 K
b0 =
b0 >
b1 >
b1 =
#1400
0!
04
#1405
1!
14
b1111 J
b10011 K
b10000 K
b0 =
b0 >
b0 *
b0 (
b0 -
b0 /
#1410
0!
04
#1415
1!
14
b10000 J
b10011 K
b1 O
b10000 K
b10 ?
b10 ,
b10 1
#1420
0!
04
#1425
1!
14
b1 N
b10011 K
b0 O
b10 O
b10000 K
#1430
0!
04
#1435
1!
14
b10 N
b10011 K
b0 O
b11 O
b10000 K
#1440
0!
04
#1445
1!
14
b11 N
b10011 K
b0 O
b100 O
b10000 K
#1450
0!
04
#1455
1!
14
b100 N
b10011 K
b0 O
b101 O
b10000 K
#1460
0!
04
#1465
1!
14
b101 N
b10011 K
b0 O
b110 O
b10000 K
#1470
0!
04
#1475
1!
14
b110 N
b10011 K
b0 O
b111 O
b10000 K
#1480
0!
04
#1485
1!
14
b111 N
b10011 K
b0 O
b1000 O
b10000 K
#1490
0!
04
#1495
1!
14
b1000 N
b10011 K
b0 O
b1001 O
b10000 K
#1500
0!
04
#1505
1!
14
b1001 N
b10011 K
b0 O
b1010 O
b10001 K
b0 O
#1510
0!
04
#1515
1!
14
b10001 J
b0 N
b10011 K
b10010 K
b0 ?
b1 ?
b1 ,
b1 1
#1520
0!
04
#1525
1!
14
b10010 J
b10011 K
b0 ?
b1 ?
#1530
0!
04
#1535
1!
14
b10011 J
b0 K
b0 ?
b0 ,
b0 1
#1540
0!
04
#1545
1!
14
b0 J
b10011 K
b1 O
b0 K
b10 ;
b10 <
b10 +
b10 )
b10 .
b10 0
#1550
0!
04
#1555
1!
14
b1 N
b10011 K
b0 O
b10 O
b0 K
#1560
0!
04
#1565
1!
14
b10 N
b10011 K
b0 O
b11 O
b0 K
#1570
0!
04
#1575
1!
14
b11 N
b10011 K
b0 O
b100 O
b0 K
#1580
0!
04
#1585
1!
14
b100 N
b10011 K
b0 O
b101 O
b0 K
#1590
0!
04
#1595
1!
14
b101 N
b10011 K
b0 O
b110 O
b0 K
#1600
0!
04
